Metadata-Version: 2.4
Name: ros-rosidl-default-generators
Version: 1.7.1
Summary: Wheel for the rosidl_default_generators (ros-rosidl-default-generators) ROS 2 package.
Dynamic: description
Dynamic: description-content-type
Dynamic: summary
